[
  {
    "name": "Abraham Lincoln",
    "party": "Republican"
  },
  {
    "name": "Ulysses S. Grant",
    "party": "Republican"
  },
  {
    "name": "Rutherford B. Hayes",
    "party": "Republican"
  },
  {
    "name": "James A. Garfield",
    "party": "Republican"
  },
  {
    "name": "Chester A. Arthur",
    "party": "Republican"
  },
  {
    "name": "Benjamin Harrison",
    "party": "Republican"
  },
  {
    "name": "William McKinley",
    "party": "Republican"
  },
  {
    "name": "Theodore Roosevelt",
    "party": "Republican"
  },
  {
    "name": "William Howard Taft",
    "party": "Republican"
  },
  {
    "name": "Warren G. Harding",
    "party": "Republican"
  },
  {
    "name": "Calvin Coolidge",
    "party": "Republican"
  },
  {
    "name": "Herbert Hoover",
    "party": "Republican"
  },
  {
    "name": "Dwight D. Eisenhower",
    "party": "Republican"
  },
  {
    "name": "Richard Nixon",
    "party": "Republican"
  },
  {
    "name": "Gerald Ford",
    "party": "Republican"
  },
  {
    "name": "Ronald Reagan",
    "party": "Republican"
  },
  {
    "name": "George H.W. Bush",
    "party": "Republican"
  },
  {
    "name": "George W. Bush",
    "party": "Republican"
  },
  {
    "name": "Donald Trump",
    "party": "Republican"
  }
]